chilean_ci/__init__.py
chilean_ci/chilean_ci.py
chilean_ci-0.0.1.dist-info/LICENSE
chilean_ci-0.0.1.dist-info/METADATA
chilean_ci-0.0.1.dist-info/WHEEL
chilean_ci-0.0.1.dist-info/top_level.txt
chilean_ci-0.0.1.dist-info/RECORD
