Metadata-Version: 2.1
Name: chilean-ci
Version: 0.0.1
Summary: A simple class for work with Chilean CI (RUT)
Home-page: https://github.com/ceslat/chileanci
Author: CesLat
Author-email: cesar.latorre@gmail.com
License: UNKNOWN
Project-URL: Bug Tracker, https://github.com/ceslat/chileanci/issues
Platform: UNKNOWN
Classifier: Programming Language :: Python :: 3
Classifier: License :: OSI Approved :: MIT License
Classifier: Operating System :: OS Independent
Requires-Python: >=3.6
License-File: LICENSE
